bnglonlat/__init__.py
bnglonlat/_bnglonlat.py
bnglonlat/tests/__init__.py
bnglonlat/tests/test_bnglonlat.py
bnglonlat-0.0.1.dist-info/METADATA
bnglonlat-0.0.1.dist-info/WHEEL
bnglonlat-0.0.1.dist-info/top_level.txt
bnglonlat-0.0.1.dist-info/RECORD
