Metadata-Version: 2.1
Name: bnglonlat
Version: 0.0.1
Summary: Pure python port of convertbng.util.convert_lonlat.
Home-page: https://github.com/MichaelClerx/bnglonlat
Author: Michael Clerx
Author-email: work@michaelclerx.com
License: MIT license
Project-URL: Bug Tracker, https://github.com/MichaelClerx/bnglonlat/issues
Project-URL: Source Code, https://github.com/MichaelClerx/bnglonlat
Platform: UNKNOWN
Classifier: Development Status :: 3 - Alpha
Classifier: Intended Audience :: Science/Research
Classifier: License :: OSI Approved :: MIT License
Classifier: Operating System :: OS Independent
Classifier: Programming Language :: Python :: 3
Classifier: Topic :: Scientific/Engineering
Requires-Dist: numpy
Provides-Extra: dev
Requires-Dist: flake8 (>=3) ; extra == 'dev'
Requires-Dist: convertbng (>=0.6.32) ; extra == 'dev'
